telenet/__init__.py
telenet/client.py
telenet/exceptions.py
telenet/filters.py
telenet/keyboards.py
telenet/middleware.py
telenet/router.py
telenet/types.py
telenet/webhook.py
telenet/storage/__init__.py
telenet/storage/memory.py
telenet/utils/__init__.py
telenet/utils/backoff.py
telenet/utils/logger.py
telenet/utils/rate_limit.py
telenet-2.7.0.dist-info/METADATA
telenet-2.7.0.dist-info/WHEEL
telenet-2.7.0.dist-info/top_level.txt
telenet-2.7.0.dist-info/RECORD
