Metadata-Version: 2.4
Name: telenet
Version: 2.7.0
Summary: TeleNet: Async Telegram Bot API framework
Author-email: Ali Jafari <thealiapi@gmail.com>
Requires-Python: >=3.9
Requires-Dist: aiohttp>=3.9
